{
  "status": "success",
  "topics": {
    "top": [
      {
        "query": "Bài hát",
        "value": 100,
        "formattedValue": "100",
        "raw": {
          "topic": {
            "mid": "/m/074ft",
            "title": "Bài hát",
            "type": "Loại sáng tác"
          },
          "value": 100,
          "formattedValue": "100",
          "hasData": true,
          "link": "/trends/explore?q=/m/074ft&date=now+7-d&geo=IL"
        }
      },
      {
        "query": "Trẻ em",
        "value": 24,
        "formattedValue": "24",
        "raw": {
          "topic": {
            "mid": "/m/0ytgt",
            "title": "Trẻ em",
            "type": "Chủ đề"
          },
          "value": 24,
          "formattedValue": "24",
          "hasData": true,
          "link": "/trends/explore?q=/m/0ytgt&date=now+7-d&geo=IL"
        }
      },
      {
        "query": "Điện ảnh",
        "value": 24,
        "formattedValue": "24",
        "raw": {
          "topic": {
            "mid": "/m/02vxn",
            "title": "Điện ảnh",
            "type": "Loại truyền hình"
          },
          "value": 24,
          "formattedValue": "24",
          "hasData": true,
          "link": "/trends/explore?q=/m/02vxn&date=now+7-d&geo=IL"
        }
      },
      {
        "query": "Tập phim",
        "value": 23,
        "formattedValue": "23",
        "raw": {
          "topic": {
            "mid": "/m/02cphr",
            "title": "Tập phim",
            "type": "Chủ đề"
          },
          "value": 23,
          "formattedValue": "23",
          "hasData": true,
          "link": "/trends/explore?q=/m/02cphr&date=now+7-d&geo=IL"
        }
      },
      {
        "query": "2026",
        "value": 21,
        "formattedValue": "21",
        "raw": {
          "topic": {
            "mid": "/g/11b77d6b6g",
            "title": "2026",
            "type": "Chủ đề"
          },
          "value": 21,
          "formattedValue": "21",
          "hasData": true,
          "link": "/trends/explore?q=/g/11b77d6b6g&date=now+7-d&geo=IL"
        }
      },
      {
        "query": "Âm nhạc",
        "value": 16,
        "formattedValue": "16",
        "raw": {
          "topic": {
            "mid": "/m/04rlf",
            "title": "Âm nhạc",
            "type": "Định dạng âm thanh"
          },
          "value": 16,
          "formattedValue": "16",
          "hasData": true,
          "link": "/trends/explore?q=/m/04rlf&date=now+7-d&geo=IL"
        }
      },
      {
        "query": "Chương trình truyền hình dài tập",
        "value": 12,
        "formattedValue": "12",
        "raw": {
          "topic": {
            "mid": "/g/1219y26q",
            "title": "Chương trình truyền hình dài tập",
            "type": "Chủ đề"
          },
          "value": 12,
          "formattedValue": "12",
          "hasData": true,
          "link": "/trends/explore?q=/g/1219y26q&date=now+7-d&geo=IL"
        }
      },
      {
        "query": "Giải Bóng đá Vô địch Thế giới",
        "value": 12,
        "formattedValue": "12",
        "raw": {
          "topic": {
            "mid": "/m/030q7",
            "title": "Giải Bóng đá Vô địch Thế giới",
            "type": "Giải bóng đá"
          },
          "value": 12,
          "formattedValue": "12",
          "hasData": true,
          "link": "/trends/explore?q=/m/030q7&date=now+7-d&geo=IL"
        }
      },
      {
        "query": "Tiếng Do Thái",
        "value": 10,
        "formattedValue": "10",
        "raw": {
          "topic": {
            "mid": "/m/03hkp",
            "title": "Tiếng Do Thái",
            "type": "Tiếng"
          },
          "value": 10,
          "formattedValue": "10",
          "hasData": true,
          "link": "/trends/explore?q=/m/03hkp&date=now+7-d&geo=IL"
        }
      },
      {
        "query": "Israel",
        "value": 9,
        "formattedValue": "9",
        "raw": {
          "topic": {
            "mid": "/m/03spz",
            "title": "Israel",
            "type": "Quốc gia ở Trung Đông"
          },
          "value": 9,
          "formattedValue": "9",
          "hasData": true,
          "link": "/trends/explore?q=/m/03spz&date=now+7-d&geo=IL"
        }
      },
      {
        "query": "Checkout",
        "value": 9,
        "formattedValue": "9",
        "raw": {
          "topic": {
            "mid": "/g/11hckrpymt",
            "title": "Checkout",
            "type": "Chương trình truyền hình"
          },
          "value": 9,
          "formattedValue": "9",
          "hasData": true,
          "link": "/trends/explore?q=/g/11hckrpymt&date=now+7-d&geo=IL"
        }
      },
      {
        "query": "Trò chơi",
        "value": 8,
        "formattedValue": "8",
        "raw": {
          "topic": {
            "mid": "/m/03bt1gh",
            "title": "Trò chơi",
            "type": "Chủ đề"
          },
          "value": 8,
          "formattedValue": "8",
          "hasData": true,
          "link": "/trends/explore?q=/m/03bt1gh&date=now+7-d&geo=IL"
        }
      },
      {
        "query": "Video",
        "value": 8,
        "formattedValue": "8",
        "raw": {
          "topic": {
            "mid": "/m/07z4p",
            "title": "Video",
            "type": "Định dạng phim"
          },
          "value": 8,
          "formattedValue": "8",
          "hasData": true,
          "link": "/trends/explore?q=/m/07z4p&date=now+7-d&geo=IL"
        }
      },
      {
        "query": "Mùa giải thể thao",
        "value": 8,
        "formattedValue": "8",
        "raw": {
          "topic": {
            "mid": "/m/0331gn",
            "title": "Mùa giải thể thao",
            "type": "Chủ đề"
          },
          "value": 8,
          "formattedValue": "8",
          "hasData": true,
          "link": "/trends/explore?q=/m/0331gn&date=now+7-d&geo=IL"
        }
      },
      {
        "query": "Eyal Golan",
        "value": 8,
        "formattedValue": "8",
        "raw": {
          "topic": {
            "mid": "/m/0l026y",
            "title": "Eyal Golan",
            "type": "Ca sĩ"
          },
          "value": 8,
          "formattedValue": "8",
          "hasData": true,
          "link": "/trends/explore?q=/m/0l026y&date=now+7-d&geo=IL"
        }
      },
      {
        "query": "Thầy đạo",
        "value": 7,
        "formattedValue": "7",
        "raw": {
          "topic": {
            "mid": "/m/0djbw",
            "title": "Thầy đạo",
            "type": "Vai trò của lãnh tụ tôn giáo"
          },
          "value": 7,
          "formattedValue": "7",
          "hasData": true,
          "link": "/trends/explore?q=/m/0djbw&date=now+7-d&geo=IL"
        }
      },
      {
        "query": "Âm thanh",
        "value": 7,
        "formattedValue": "7",
        "raw": {
          "topic": {
            "mid": "/m/06qc5",
            "title": "Âm thanh",
            "type": "Chủ đề"
          },
          "value": 7,
          "formattedValue": "7",
          "hasData": true,
          "link": "/trends/explore?q=/m/06qc5&date=now+7-d&geo=IL"
        }
      },
      {
        "query": "Tiếng Ả Rập",
        "value": 7,
        "formattedValue": "7",
        "raw": {
          "topic": {
            "mid": "/m/0jzc",
            "title": "Tiếng Ả Rập",
            "type": "Ngôn ngữ"
          },
          "value": 7,
          "formattedValue": "7",
          "hasData": true,
          "link": "/trends/explore?q=/m/0jzc&date=now+7-d&geo=IL"
        }
      },
      {
        "query": "Nhảy múa",
        "value": 7,
        "formattedValue": "7",
        "raw": {
          "topic": {
            "mid": "/m/026bk",
            "title": "Nhảy múa",
            "type": "Lĩnh vực nghề nghiệp"
          },
          "value": 7,
          "formattedValue": "7",
          "hasData": true,
          "link": "/trends/explore?q=/m/026bk&date=now+7-d&geo=IL"
        }
      },
      {
        "query": "Trẻ sơ sinh",
        "value": 7,
        "formattedValue": "7",
        "raw": {
          "topic": {
            "mid": "/m/0jnvp",
            "title": "Trẻ sơ sinh",
            "type": "Chủ đề"
          },
          "value": 7,
          "formattedValue": "7",
          "hasData": true,
          "link": "/trends/explore?q=/m/0jnvp&date=now+7-d&geo=IL"
        }
      },
      {
        "query": "Karaoke",
        "value": 6,
        "formattedValue": "6",
        "raw": {
          "topic": {
            "mid": "/m/04c5p",
            "title": "Karaoke",
            "type": "Chủ đề"
          },
          "value": 6,
          "formattedValue": "6",
          "hasData": true,
          "link": "/trends/explore?q=/m/04c5p&date=now+7-d&geo=IL"
        }
      },
      {
        "query": "Tình yêu",
        "value": 6,
        "formattedValue": "6",
        "raw": {
          "topic": {
            "mid": "/m/048knlz",
            "title": "Tình yêu",
            "type": "Chủ đề"
          },
          "value": 6,
          "formattedValue": "6",
          "hasData": true,
          "link": "/trends/explore?q=/m/048knlz&date=now+7-d&geo=IL"
        }
      },
      {
        "query": "Sinh nhật",
        "value": 6,
        "formattedValue": "6",
        "raw": {
          "topic": {
            "mid": "/m/01kcnl",
            "title": "Sinh nhật",
            "type": "Chủ đề"
          },
          "value": 6,
          "formattedValue": "6",
          "hasData": true,
          "link": "/trends/explore?q=/m/01kcnl&date=now+7-d&geo=IL"
        }
      },
      {
        "query": "Thế giới",
        "value": 6,
        "formattedValue": "6",
        "raw": {
          "topic": {
            "mid": "/m/09nm_",
            "title": "Thế giới",
            "type": "Chủ đề"
          },
          "value": 6,
          "formattedValue": "6",
          "hasData": true,
          "link": "/trends/explore?q=/m/09nm_&date=now+7-d&geo=IL"
        }
      },
      {
        "query": "Con gái",
        "value": 6,
        "formattedValue": "6",
        "raw": {
          "topic": {
            "mid": "/m/05r655",
            "title": "Con gái",
            "type": "Chủ đề"
          },
          "value": 6,
          "formattedValue": "6",
          "hasData": true,
          "link": "/trends/explore?q=/m/05r655&date=now+7-d&geo=IL"
        }
      }
    ],
    "rising": [
      {
        "query": "Mehubarim",
        "value": 750,
        "formattedValue": "+750%",
        "raw": {
          "topic": {
            "mid": "/g/113qbplmj",
            "title": "Mehubarim",
            "type": "Chương trình truyền hình"
          },
          "value": 750,
          "formattedValue": "+750%",
          "link": "/trends/explore?q=/g/113qbplmj&date=now+7-d&geo=IL"
        }
      },
      {
        "query": "Hà Lan",
        "value": 300,
        "formattedValue": "+300%",
        "raw": {
          "topic": {
            "mid": "/m/059j2",
            "title": "Hà Lan",
            "type": "Quốc gia ở Châu Âu"
          },
          "value": 300,
          "formattedValue": "+300%",
          "link": "/trends/explore?q=/m/059j2&date=now+7-d&geo=IL"
        }
      },
      {
        "query": "To Myself",
        "value": 250,
        "formattedValue": "+250%",
        "raw": {
          "topic": {
            "mid": "/g/11xl3vy4ss",
            "title": "To Myself",
            "type": "Chương trình truyền hình"
          },
          "value": 250,
          "formattedValue": "+250%",
          "link": "/trends/explore?q=/g/11xl3vy4ss&date=now+7-d&geo=IL"
        }
      },
      {
        "query": "Omer Levy",
        "value": 160,
        "formattedValue": "+160%",
        "raw": {
          "topic": {
            "mid": "/g/11f0yy2p2j",
            "title": "Omer Levy",
            "type": "Nhà nghiên cứu"
          },
          "value": 160,
          "formattedValue": "+160%",
          "link": "/trends/explore?q=/g/11f0yy2p2j&date=now+7-d&geo=IL"
        }
      },
      {
        "query": "Đội tuyển bóng đá quốc gia Maroc",
        "value": 90,
        "formattedValue": "+90%",
        "raw": {
          "topic": {
            "mid": "/m/03_9hm",
            "title": "Đội tuyển bóng đá quốc gia Maroc",
            "type": "Đội bóng đá"
          },
          "value": 90,
          "formattedValue": "+90%",
          "link": "/trends/explore?q=/m/03_9hm&date=now+7-d&geo=IL"
        }
      },
      {
        "query": "Eyal Levi",
        "value": 80,
        "formattedValue": "+80%",
        "raw": {
          "topic": {
            "mid": "/g/11j9fv_83q",
            "title": "Eyal Levi",
            "type": "Nghệ sĩ âm nhạc"
          },
          "value": 80,
          "formattedValue": "+80%",
          "link": "/trends/explore?q=/g/11j9fv_83q&date=now+7-d&geo=IL"
        }
      },
      {
        "query": "Maroc",
        "value": 80,
        "formattedValue": "+80%",
        "raw": {
          "topic": {
            "mid": "/m/04wgh",
            "title": "Maroc",
            "type": "Quốc gia ở Bắc Phi"
          },
          "value": 80,
          "formattedValue": "+80%",
          "link": "/trends/explore?q=/m/04wgh&date=now+7-d&geo=IL"
        }
      },
      {
        "query": "איך שהיא רוקדת",
        "value": 80,
        "formattedValue": "+80%",
        "raw": {
          "topic": {
            "mid": "/g/11zbqmzjs6",
            "title": "איך שהיא רוקדת",
            "type": "Chủ đề"
          },
          "value": 80,
          "formattedValue": "+80%",
          "link": "/trends/explore?q=/g/11zbqmzjs6&date=now+7-d&geo=IL"
        }
      },
      {
        "query": "Nhật Bản",
        "value": 60,
        "formattedValue": "+60%",
        "raw": {
          "topic": {
            "mid": "/m/03_3d",
            "title": "Nhật Bản",
            "type": "Quốc gia ở Đông Á"
          },
          "value": 60,
          "formattedValue": "+60%",
          "link": "/trends/explore?q=/m/03_3d&date=now+7-d&geo=IL"
        }
      },
      {
        "query": "Đội tuyển Bóng đá Quốc gia Brasil",
        "value": 60,
        "formattedValue": "+60%",
        "raw": {
          "topic": {
            "mid": "/m/01352_",
            "title": "Đội tuyển Bóng đá Quốc gia Brasil",
            "type": "Đội bóng đá"
          },
          "value": 60,
          "formattedValue": "+60%",
          "link": "/trends/explore?q=/m/01352_&date=now+7-d&geo=IL"
        }
      },
      {
        "query": "Big Brother",
        "value": 50,
        "formattedValue": "+50%",
        "raw": {
          "topic": {
            "mid": "/m/04ldr17",
            "title": "Big Brother",
            "type": "Chương trình truyền hình"
          },
          "value": 50,
          "formattedValue": "+50%",
          "link": "/trends/explore?q=/m/04ldr17&date=now+7-d&geo=IL"
        }
      },
      {
        "query": "Hỗn loạn",
        "value": 50,
        "formattedValue": "+50%",
        "raw": {
          "topic": {
            "mid": "/m/012vxpx6",
            "title": "Hỗn loạn",
            "type": "Bộ phim hài"
          },
          "value": 50,
          "formattedValue": "+50%",
          "link": "/trends/explore?q=/m/012vxpx6&date=now+7-d&geo=IL"
        }
      },
      {
        "query": "Al Shami",
        "value": 50,
        "formattedValue": "+50%",
        "raw": {
          "topic": {
            "mid": "/g/11txyph5rn",
            "title": "Al Shami",
            "type": "Ca sĩ"
          },
          "value": 50,
          "formattedValue": "+50%",
          "link": "/trends/explore?q=/g/11txyph5rn&date=now+7-d&geo=IL"
        }
      },
      {
        "query": "Đội tuyển Bóng đá Quốc gia Pháp",
        "value": 40,
        "formattedValue": "+40%",
        "raw": {
          "topic": {
            "mid": "/m/01l3vx",
            "title": "Đội tuyển Bóng đá Quốc gia Pháp",
            "type": "Đội bóng đá"
          },
          "value": 40,
          "formattedValue": "+40%",
          "link": "/trends/explore?q=/m/01l3vx&date=now+7-d&geo=IL"
        }
      }
    ]
  },
  "queries": {
    "top": [
      {
        "query": "اغاني",
        "value": 100,
        "formattedValue": "100",
        "raw": {
          "query": "اغاني",
          "value": 100,
          "formattedValue": "100",
          "hasData": true,
          "link": "/trends/explore?q=%D8%A7%D8%BA%D8%A7%D9%86%D9%8A&date=now+7-d&geo=IL"
        }
      },
      {
        "query": "שירים",
        "value": 92,
        "formattedValue": "92",
        "raw": {
          "query": "שירים",
          "value": 92,
          "formattedValue": "92",
          "hasData": true,
          "link": "/trends/explore?q=%D7%A9%D7%99%D7%A8%D7%99%D7%9D&date=now+7-d&geo=IL"
        }
      },
      {
        "query": "קופה ראשית",
        "value": 42,
        "formattedValue": "42",
        "raw": {
          "query": "קופה ראשית",
          "value": 42,
          "formattedValue": "42",
          "hasData": true,
          "link": "/trends/explore?q=%D7%A7%D7%95%D7%A4%D7%94+%D7%A8%D7%90%D7%A9%D7%99%D7%AA&date=now+7-d&geo=IL"
        }
      },
      {
        "query": "music",
        "value": 35,
        "formattedValue": "35",
        "raw": {
          "query": "music",
          "value": 35,
          "formattedValue": "35",
          "hasData": true,
          "link": "/trends/explore?q=music&date=now+7-d&geo=IL"
        }
      },
      {
        "query": "אייל גולן",
        "value": 31,
        "formattedValue": "31",
        "raw": {
          "query": "אייל גולן",
          "value": 31,
          "formattedValue": "31",
          "hasData": true,
          "link": "/trends/explore?q=%D7%90%D7%99%D7%99%D7%9C+%D7%92%D7%95%D7%9C%D7%9F&date=now+7-d&geo=IL"
        }
      },
      {
        "query": "اغنيه",
        "value": 31,
        "formattedValue": "31",
        "raw": {
          "query": "اغنيه",
          "value": 31,
          "formattedValue": "31",
          "hasData": true,
          "link": "/trends/explore?q=%D8%A7%D8%BA%D9%86%D9%8A%D9%87&date=now+7-d&geo=IL"
        }
      },
      {
        "query": "מלון הוטל",
        "value": 27,
        "formattedValue": "27",
        "raw": {
          "query": "מלון הוטל",
          "value": 27,
          "formattedValue": "27",
          "hasData": true,
          "link": "/trends/explore?q=%D7%9E%D7%9C%D7%95%D7%9F+%D7%94%D7%95%D7%98%D7%9C&date=now+7-d&geo=IL"
        }
      },
      {
        "query": "עומר אדם",
        "value": 27,
        "formattedValue": "27",
        "raw": {
          "query": "עומר אדם",
          "value": 27,
          "formattedValue": "27",
          "hasData": true,
          "link": "/trends/explore?q=%D7%A2%D7%95%D7%9E%D7%A8+%D7%90%D7%93%D7%9D&date=now+7-d&geo=IL"
        }
      },
      {
        "query": "songs",
        "value": 22,
        "formattedValue": "22",
        "raw": {
          "query": "songs",
          "value": 22,
          "formattedValue": "22",
          "hasData": true,
          "link": "/trends/explore?q=songs&date=now+7-d&geo=IL"
        }
      },
      {
        "query": "קריוקי",
        "value": 20,
        "formattedValue": "20",
        "raw": {
          "query": "קריוקי",
          "value": 20,
          "formattedValue": "20",
          "hasData": true,
          "link": "/trends/explore?q=%D7%A7%D7%A8%D7%99%D7%95%D7%A7%D7%99&date=now+7-d&geo=IL"
        }
      },
      {
        "query": "اطفال",
        "value": 20,
        "formattedValue": "20",
        "raw": {
          "query": "اطفال",
          "value": 20,
          "formattedValue": "20",
          "hasData": true,
          "link": "/trends/explore?q=%D8%A7%D8%B7%D9%81%D8%A7%D9%84&date=now+7-d&geo=IL"
        }
      },
      {
        "query": "מונדיאל",
        "value": 20,
        "formattedValue": "20",
        "raw": {
          "query": "מונדיאל",
          "value": 20,
          "formattedValue": "20",
          "hasData": true,
          "link": "/trends/explore?q=%D7%9E%D7%95%D7%A0%D7%93%D7%99%D7%90%D7%9C&date=now+7-d&geo=IL"
        }
      },
      {
        "query": "משפחת טרסוב",
        "value": 19,
        "formattedValue": "19",
        "raw": {
          "query": "משפחת טרסוב",
          "value": 19,
          "formattedValue": "19",
          "hasData": true,
          "link": "/trends/explore?q=%D7%9E%D7%A9%D7%A4%D7%97%D7%AA+%D7%98%D7%A8%D7%A1%D7%95%D7%91&date=now+7-d&geo=IL"
        }
      },
      {
        "query": "בן צור",
        "value": 17,
        "formattedValue": "17",
        "raw": {
          "query": "בן צור",
          "value": 17,
          "formattedValue": "17",
          "hasData": true,
          "link": "/trends/explore?q=%D7%91%D7%9F+%D7%A6%D7%95%D7%A8&date=now+7-d&geo=IL"
        }
      },
      {
        "query": "פאר טסי",
        "value": 16,
        "formattedValue": "16",
        "raw": {
          "query": "פאר טסי",
          "value": 16,
          "formattedValue": "16",
          "hasData": true,
          "link": "/trends/explore?q=%D7%A4%D7%90%D7%A8+%D7%98%D7%A1%D7%99&date=now+7-d&geo=IL"
        }
      },
      {
        "query": "יום הולדת",
        "value": 16,
        "formattedValue": "16",
        "raw": {
          "query": "יום הולדת",
          "value": 16,
          "formattedValue": "16",
          "hasData": true,
          "link": "/trends/explore?q=%D7%99%D7%95%D7%9D+%D7%94%D7%95%D7%9C%D7%93%D7%AA&date=now+7-d&geo=IL"
        }
      },
      {
        "query": "شفا",
        "value": 16,
        "formattedValue": "16",
        "raw": {
          "query": "شفا",
          "value": 16,
          "formattedValue": "16",
          "hasData": true,
          "link": "/trends/explore?q=%D8%B4%D9%81%D8%A7&date=now+7-d&geo=IL"
        }
      },
      {
        "query": "شفا شفا",
        "value": 16,
        "formattedValue": "16",
        "raw": {
          "query": "شفا شفا",
          "value": 16,
          "formattedValue": "16",
          "hasData": true,
          "link": "/trends/explore?q=%D8%B4%D9%81%D8%A7+%D8%B4%D9%81%D8%A7&date=now+7-d&geo=IL"
        }
      },
      {
        "query": "מישל",
        "value": 16,
        "formattedValue": "16",
        "raw": {
          "query": "מישל",
          "value": 16,
          "formattedValue": "16",
          "hasData": true,
          "link": "/trends/explore?q=%D7%9E%D7%99%D7%A9%D7%9C&date=now+7-d&geo=IL"
        }
      },
      {
        "query": "אודיה",
        "value": 15,
        "formattedValue": "15",
        "raw": {
          "query": "אודיה",
          "value": 15,
          "formattedValue": "15",
          "hasData": true,
          "link": "/trends/explore?q=%D7%90%D7%95%D7%93%D7%99%D7%94&date=now+7-d&geo=IL"
        }
      },
      {
        "query": "איתי לוי",
        "value": 15,
        "formattedValue": "15",
        "raw": {
          "query": "איתי לוי",
          "value": 15,
          "formattedValue": "15",
          "hasData": true,
          "link": "/trends/explore?q=%D7%90%D7%99%D7%AA%D7%99+%D7%9C%D7%95%D7%99&date=now+7-d&geo=IL"
        }
      },
      {
        "query": "לבד בבית",
        "value": 13,
        "formattedValue": "13",
        "raw": {
          "query": "לבד בבית",
          "value": 13,
          "formattedValue": "13",
          "hasData": true,
          "link": "/trends/explore?q=%D7%9C%D7%91%D7%93+%D7%91%D7%91%D7%99%D7%AA&date=now+7-d&geo=IL"
        }
      },
      {
        "query": "אבא",
        "value": 13,
        "formattedValue": "13",
        "raw": {
          "query": "אבא",
          "value": 13,
          "formattedValue": "13",
          "hasData": true,
          "link": "/trends/explore?q=%D7%90%D7%91%D7%90&date=now+7-d&geo=IL"
        }
      },
      {
        "query": "סולטיז",
        "value": 13,
        "formattedValue": "13",
        "raw": {
          "query": "סולטיז",
          "value": 13,
          "formattedValue": "13",
          "hasData": true,
          "link": "/trends/explore?q=%D7%A1%D7%95%D7%9C%D7%98%D7%99%D7%96&date=now+7-d&geo=IL"
        }
      },
      {
        "query": "قران",
        "value": 13,
        "formattedValue": "13",
        "raw": {
          "query": "قران",
          "value": 13,
          "formattedValue": "13",
          "hasData": true,
          "link": "/trends/explore?q=%D9%82%D8%B1%D8%A7%D9%86&date=now+7-d&geo=IL"
        }
      }
    ],
    "rising": [
      {
        "query": "הרב עמוס גואטה",
        "value": 3000,
        "formattedValue": "+3.000%",
        "raw": {
          "query": "הרב עמוס גואטה",
          "value": 3000,
          "formattedValue": "+3.000%",
          "link": "/trends/explore?q=%D7%94%D7%A8%D7%91+%D7%A2%D7%9E%D7%95%D7%A1+%D7%92%D7%95%D7%90%D7%98%D7%94&date=now+7-d&geo=IL"
        }
      },
      {
        "query": "צרפת נגד שוודיה",
        "value": 1400,
        "formattedValue": "+1.400%",
        "raw": {
          "query": "צרפת נגד שוודיה",
          "value": 1400,
          "formattedValue": "+1.400%",
          "link": "/trends/explore?q=%D7%A6%D7%A8%D7%A4%D7%AA+%D7%A0%D7%92%D7%93+%D7%A9%D7%95%D7%95%D7%93%D7%99%D7%94&date=now+7-d&geo=IL"
        }
      },
      {
        "query": "ארגנטינה נגד ירדן",
        "value": 1300,
        "formattedValue": "+1.300%",
        "raw": {
          "query": "ארגנטינה נגד ירדן",
          "value": 1300,
          "formattedValue": "+1.300%",
          "link": "/trends/explore?q=%D7%90%D7%A8%D7%92%D7%A0%D7%98%D7%99%D7%A0%D7%94+%D7%A0%D7%92%D7%93+%D7%99%D7%A8%D7%93%D7%9F&date=now+7-d&geo=IL"
        }
      },
      {
        "query": "רבי עמוס גואטה",
        "value": 1050,
        "formattedValue": "+1.050%",
        "raw": {
          "query": "רבי עמוס גואטה",
          "value": 1050,
          "formattedValue": "+1.050%",
          "link": "/trends/explore?q=%D7%A8%D7%91%D7%99+%D7%A2%D7%9E%D7%95%D7%A1+%D7%92%D7%95%D7%90%D7%98%D7%94&date=now+7-d&geo=IL"
        }
      },
      {
        "query": "citizen vigilante",
        "value": 950,
        "formattedValue": "+950%",
        "raw": {
          "query": "citizen vigilante",
          "value": 950,
          "formattedValue": "+950%",
          "link": "/trends/explore?q=citizen+vigilante&date=now+7-d&geo=IL"
        }
      },
      {
        "query": "מחוברים",
        "value": 650,
        "formattedValue": "+650%",
        "raw": {
          "query": "מחוברים",
          "value": 650,
          "formattedValue": "+650%",
          "link": "/trends/explore?q=%D7%9E%D7%97%D7%95%D7%91%D7%A8%D7%99%D7%9D&date=now+7-d&geo=IL"
        }
      },
      {
        "query": "אל עצמי עונה 2",
        "value": 200,
        "formattedValue": "+200%",
        "raw": {
          "query": "אל עצמי עונה 2",
          "value": 200,
          "formattedValue": "+200%",
          "link": "/trends/explore?q=%D7%90%D7%9C+%D7%A2%D7%A6%D7%9E%D7%99+%D7%A2%D7%95%D7%A0%D7%94+2&date=now+7-d&geo=IL"
        }
      },
      {
        "query": "אל עצמי",
        "value": 200,
        "formattedValue": "+200%",
        "raw": {
          "query": "אל עצמי",
          "value": 200,
          "formattedValue": "+200%",
          "link": "/trends/explore?q=%D7%90%D7%9C+%D7%A2%D7%A6%D7%9E%D7%99&date=now+7-d&geo=IL"
        }
      },
      {
        "query": "אבי הטחול",
        "value": 190,
        "formattedValue": "+190%",
        "raw": {
          "query": "אבי הטחול",
          "value": 190,
          "formattedValue": "+190%",
          "link": "/trends/explore?q=%D7%90%D7%91%D7%99+%D7%94%D7%98%D7%97%D7%95%D7%9C&date=now+7-d&geo=IL"
        }
      },
      {
        "query": "עומר לוי",
        "value": 130,
        "formattedValue": "+130%",
        "raw": {
          "query": "עומר לוי",
          "value": 130,
          "formattedValue": "+130%",
          "link": "/trends/explore?q=%D7%A2%D7%95%D7%9E%D7%A8+%D7%9C%D7%95%D7%99&date=now+7-d&geo=IL"
        }
      },
      {
        "query": "اه يا حلو",
        "value": 110,
        "formattedValue": "+110%",
        "raw": {
          "query": "اه يا حلو",
          "value": 110,
          "formattedValue": "+110%",
          "link": "/trends/explore?q=%D8%A7%D9%87+%D9%8A%D8%A7+%D8%AD%D9%84%D9%88&date=now+7-d&geo=IL"
        }
      },
      {
        "query": "قسمة ونصيب",
        "value": 80,
        "formattedValue": "+80%",
        "raw": {
          "query": "قسمة ونصيب",
          "value": 80,
          "formattedValue": "+80%",
          "link": "/trends/explore?q=%D9%82%D8%B3%D9%85%D8%A9+%D9%88%D9%86%D8%B5%D9%8A%D8%A8&date=now+7-d&geo=IL"
        }
      },
      {
        "query": "غيث مروان",
        "value": 70,
        "formattedValue": "+70%",
        "raw": {
          "query": "غيث مروان",
          "value": 70,
          "formattedValue": "+70%",
          "link": "/trends/explore?q=%D8%BA%D9%8A%D8%AB+%D9%85%D8%B1%D9%88%D8%A7%D9%86&date=now+7-d&geo=IL"
        }
      },
      {
        "query": "beni al",
        "value": 70,
        "formattedValue": "+70%",
        "raw": {
          "query": "beni al",
          "value": 70,
          "formattedValue": "+70%",
          "link": "/trends/explore?q=beni+al&date=now+7-d&geo=IL"
        }
      },
      {
        "query": "פאודה עונה 5 פרק 1 המלא",
        "value": 70,
        "formattedValue": "+70%",
        "raw": {
          "query": "פאודה עונה 5 פרק 1 המלא",
          "value": 70,
          "formattedValue": "+70%",
          "link": "/trends/explore?q=%D7%A4%D7%90%D7%95%D7%93%D7%94+%D7%A2%D7%95%D7%A0%D7%94+5+%D7%A4%D7%A8%D7%A7+1+%D7%94%D7%9E%D7%9C%D7%90&date=now+7-d&geo=IL"
        }
      },
      {
        "query": "official audio",
        "value": 70,
        "formattedValue": "+70%",
        "raw": {
          "query": "official audio",
          "value": 70,
          "formattedValue": "+70%",
          "link": "/trends/explore?q=official+audio&date=now+7-d&geo=IL"
        }
      },
      {
        "query": "topic",
        "value": 60,
        "formattedValue": "+60%",
        "raw": {
          "query": "topic",
          "value": 60,
          "formattedValue": "+60%",
          "link": "/trends/explore?q=topic&date=now+7-d&geo=IL"
        }
      },
      {
        "query": "פאודה עונה 5",
        "value": 60,
        "formattedValue": "+60%",
        "raw": {
          "query": "פאודה עונה 5",
          "value": 60,
          "formattedValue": "+60%",
          "link": "/trends/explore?q=%D7%A4%D7%90%D7%95%D7%93%D7%94+%D7%A2%D7%95%D7%A0%D7%94+5&date=now+7-d&geo=IL"
        }
      },
      {
        "query": "אייל לוי",
        "value": 60,
        "formattedValue": "+60%",
        "raw": {
          "query": "אייל לוי",
          "value": 60,
          "formattedValue": "+60%",
          "link": "/trends/explore?q=%D7%90%D7%99%D7%99%D7%9C+%D7%9C%D7%95%D7%99&date=now+7-d&geo=IL"
        }
      },
      {
        "query": "פאודה",
        "value": 60,
        "formattedValue": "+60%",
        "raw": {
          "query": "פאודה",
          "value": 60,
          "formattedValue": "+60%",
          "link": "/trends/explore?q=%D7%A4%D7%90%D7%95%D7%93%D7%94&date=now+7-d&geo=IL"
        }
      },
      {
        "query": "08",
        "value": 50,
        "formattedValue": "+50%",
        "raw": {
          "query": "08",
          "value": 50,
          "formattedValue": "+50%",
          "link": "/trends/explore?q=08&date=now+7-d&geo=IL"
        }
      },
      {
        "query": "האח הגדול",
        "value": 50,
        "formattedValue": "+50%",
        "raw": {
          "query": "האח הגדול",
          "value": 50,
          "formattedValue": "+50%",
          "link": "/trends/explore?q=%D7%94%D7%90%D7%97+%D7%94%D7%92%D7%93%D7%95%D7%9C&date=now+7-d&geo=IL"
        }
      },
      {
        "query": "שחר חסון",
        "value": 50,
        "formattedValue": "+50%",
        "raw": {
          "query": "שחר חסון",
          "value": 50,
          "formattedValue": "+50%",
          "link": "/trends/explore?q=%D7%A9%D7%97%D7%A8+%D7%97%D7%A1%D7%95%D7%9F&date=now+7-d&geo=IL"
        }
      },
      {
        "query": "brawl stars",
        "value": 50,
        "formattedValue": "+50%",
        "raw": {
          "query": "brawl stars",
          "value": 50,
          "formattedValue": "+50%",
          "link": "/trends/explore?q=brawl+stars&date=now+7-d&geo=IL"
        }
      },
      {
        "query": "דושי",
        "value": 50,
        "formattedValue": "+50%",
        "raw": {
          "query": "דושי",
          "value": 50,
          "formattedValue": "+50%",
          "link": "/trends/explore?q=%D7%93%D7%95%D7%A9%D7%99&date=now+7-d&geo=IL"
        }
      }
    ]
  }
}